projectscheduler/__init__.py
projectscheduler/gantt.py
projectscheduler/plot.py
projectscheduler-0.6.0.dist-info/entry_points.txt
projectscheduler-0.6.0.dist-info/LICENSE
projectscheduler-0.6.0.dist-info/WHEEL
projectscheduler-0.6.0.dist-info/METADATA
projectscheduler-0.6.0.dist-info/RECORD
