Metadata-Version: 2.1
Name: projectscheduler
Version: 0.6.0
Summary: Simple project scheduling tool
Home-page: https://github.com/traherom/simple-scheduler
License: MIT
Keywords: packaging,poetry
Author: Ryan Morehart
Author-email: ryan@moreharts.com
Requires-Python: >=3.6,<4.0
Classifier: License :: OSI Approved :: MIT License
Classifier: Programming Language :: Python :: 3
Classifier: Programming Language :: Python :: 3.6
Classifier: Programming Language :: Python :: 3.7
Requires-Dist: svgwrite (>=1.2,<2.0)
Project-URL: Repository, https://github.com/traherom/simple-scheduler
